hcm_causal/__init__.py
hcm_causal/dagma/__init__.py
hcm_causal/dagma/dagma_linear.py
hcm_causal/dagma/dagma_nonlinear.py
hcm_causal/dagma/locally_connected.py
hcm_causal/dagma/utils.py
hcm_causal/notears/__init__.py
hcm_causal/notears/lbfgsb_scipy.py
hcm_causal/notears/linear.py
hcm_causal/notears/locally_connected.py
hcm_causal/notears/nonlinear.py
hcm_causal/notears/trace_expm.py
hcm_causal/notears/utils.py
hcm_causal/pytetrad/__init__.py
hcm_causal/pytetrad/algcomparison_fci_algs.py
hcm_causal/pytetrad/algcomparison_large_fges.py
hcm_causal/pytetrad/compare_projects_fci.py
hcm_causal/pytetrad/compare_projects_pc.py
hcm_causal/pytetrad/compare_projects_pc_kci.py
hcm_causal/pytetrad/convert_datasets.py
hcm_causal/pytetrad/general_scoring_example.py
hcm_causal/pytetrad/proxy_testing.py
hcm_causal/pytetrad/render_gdot.py
hcm_causal/pytetrad/run_TetradSearch.py
hcm_causal/pytetrad/run_continuous.py
hcm_causal/pytetrad/run_discrete.py
hcm_causal/pytetrad/run_mixed.py
hcm_causal/pytetrad/run_with_bootstrapping.py
hcm_causal/pytetrad/simulate_continuous.py
hcm_causal/pytetrad/simulate_discrete.py
hcm_causal/pytetrad/simulate_lee_hastie.py
hcm_causal/pytetrad/R/DOCUMENTATION.md
hcm_causal/pytetrad/R/INSTALLATION.md
hcm_causal/pytetrad/R/README.md
hcm_causal/pytetrad/R/__init__.py
hcm_causal/pytetrad/R/sample_r_code1.R
hcm_causal/pytetrad/R/sample_r_code2.R
hcm_causal/pytetrad/R/sample_r_code3.R
hcm_causal/pytetrad/R/sample_r_code4.R
hcm_causal/pytetrad/R/sample_r_code5.R
hcm_causal/pytetrad/R/sample_r_code6.R
hcm_causal/pytetrad/resources/__init__.py
hcm_causal/pytetrad/resources/airfoil-self-noise.continuous.txt
hcm_causal/pytetrad/resources/auto-mpg.data.mixed.max.3.categories.txt
hcm_causal/pytetrad/resources/bridges.data.version21.txt
hcm_causal/pytetrad/resources/bridges.data.version211_rev.txt
hcm_causal/pytetrad/resources/example_sim_100-2-1000.txt
hcm_causal/pytetrad/resources/example_sim_100-6-1000.txt
hcm_causal/pytetrad/resources/knowledge.txt
hcm_causal-0.2.1.dist-info/LICENSE
hcm_causal-0.2.1.dist-info/METADATA
hcm_causal-0.2.1.dist-info/WHEEL
hcm_causal-0.2.1.dist-info/top_level.txt
hcm_causal-0.2.1.dist-info/RECORD
