Metadata-Version: 2.1
Name: hcm-causal
Version: 0.2.1
Summary: hcm_causal Python Package
Home-page: https://github.com/haharay/hcm_causal
Author: 
Classifier: Programming Language :: Python :: 3
Classifier: License :: OSI Approved :: MIT License
Classifier: Operating System :: OS Independent
Requires-Python: >=3.9
License-File: LICENSE
Requires-Dist: numpy
Requires-Dist: scipy
Requires-Dist: pandas
Requires-Dist: JPype1
Requires-Dist: causal-learn
Requires-Dist: python-igraph
Requires-Dist: torch
Requires-Dist: tqdm
Requires-Dist: scikit-learn
Requires-Dist: toolz
Requires-Dist: bayesian-optimization (>=1.1.0)
